{
  "id": "7ba5a1db-3fb0-41bb-88d4-0e3917c46adc",
  "prevId": "00000000-0000-0000-0000-000000000000",
  "version": "7",
  "dialect": "postgresql",
  "tables": {
    "public.category": {
      "name": "category",
      "schema": "",
      "columns": {
        "id_category": {
          "name": "id_category",
          "type": "uuid",
          "primaryKey": true,
          "notNull": true,
          "default": "gen_random_uuid()"
        },
        "name": {
          "name": "name",
          "type": "varchar(255)",
          "primaryKey": false,
          "notNull": true
        }
      },
      "indexes": {},
      "foreignKeys": {},
      "compositePrimaryKeys": {},
      "uniqueConstraints": {
        "category_name_unique": {
          "name": "category_name_unique",
          "nullsNotDistinct": false,
          "columns": [
            "name"
          ]
        }
      },
      "policies": {},
      "checkConstraints": {},
      "isRLSEnabled": false
    },
    "public.goods_receipt_item": {
      "name": "goods_receipt_item",
      "schema": "",
      "columns": {
        "id_receipt_item": {
          "name": "id_receipt_item",
          "type": "uuid",
          "primaryKey": true,
          "notNull": true,
          "default": "gen_random_uuid()"
        },
        "receipt_id": {
          "name": "receipt_id",
          "type": "varchar(20)",
          "primaryKey": false,
          "notNull": true
        },
        "item_id": {
          "name": "item_id",
          "type": "varchar(20)",
          "primaryKey": false,
          "notNull": true
        },
        "qty_received": {
          "name": "qty_received",
          "type": "numeric",
          "primaryKey": false,
          "notNull": true
        },
        "qty_damaged": {
          "name": "qty_damaged",
          "type": "numeric",
          "primaryKey": false,
          "notNull": true,
          "default": "'0'"
        },
        "notes": {
          "name": "notes",
          "type": "text",
          "primaryKey": false,
          "notNull": false
        }
      },
      "indexes": {},
      "foreignKeys": {
        "goods_receipt_item_receipt_id_goods_receipt_id_receipt_fk": {
          "name": "goods_receipt_item_receipt_id_goods_receipt_id_receipt_fk",
          "tableFrom": "goods_receipt_item",
          "tableTo": "goods_receipt",
          "columnsFrom": [
            "receipt_id"
          ],
          "columnsTo": [
            "id_receipt"
          ],
          "onDelete": "cascade",
          "onUpdate": "no action"
        },
        "goods_receipt_item_item_id_item_id_item_fk": {
          "name": "goods_receipt_item_item_id_item_id_item_fk",
          "tableFrom": "goods_receipt_item",
          "tableTo": "item",
          "columnsFrom": [
            "item_id"
          ],
          "columnsTo": [
            "id_item"
          ],
          "onDelete": "no action",
          "onUpdate": "no action"
        }
      },
      "compositePrimaryKeys": {},
      "uniqueConstraints": {},
      "policies": {},
      "checkConstraints": {},
      "isRLSEnabled": false
    },
    "public.goods_receipt": {
      "name": "goods_receipt",
      "schema": "",
      "columns": {
        "id_receipt": {
          "name": "id_receipt",
          "type": "varchar(20)",
          "primaryKey": true,
          "notNull": true
        },
        "purchase_id": {
          "name": "purchase_id",
          "type": "varchar(20)",
          "primaryKey": false,
          "notNull": true
        },
        "received_by": {
          "name": "received_by",
          "type": "uuid",
          "primaryKey": false,
          "notNull": true
        },
        "created_at": {
          "name": "created_at",
          "type": "timestamp",
          "primaryKey": false,
          "notNull": true,
          "default": "now()"
        }
      },
      "indexes": {},
      "foreignKeys": {
        "goods_receipt_purchase_id_purchase_id_purchase_fk": {
          "name": "goods_receipt_purchase_id_purchase_id_purchase_fk",
          "tableFrom": "goods_receipt",
          "tableTo": "purchase",
          "columnsFrom": [
            "purchase_id"
          ],
          "columnsTo": [
            "id_purchase"
          ],
          "onDelete": "no action",
          "onUpdate": "no action"
        },
        "goods_receipt_received_by_user_id_user_fk": {
          "name": "goods_receipt_received_by_user_id_user_fk",
          "tableFrom": "goods_receipt",
          "tableTo": "user",
          "columnsFrom": [
            "received_by"
          ],
          "columnsTo": [
            "id_user"
          ],
          "onDelete": "no action",
          "onUpdate": "no action"
        }
      },
      "compositePrimaryKeys": {},
      "uniqueConstraints": {},
      "policies": {},
      "checkConstraints": {},
      "isRLSEnabled": false
    },
    "public.item_bom_detail": {
      "name": "item_bom_detail",
      "schema": "",
      "columns": {
        "id_bom_detail": {
          "name": "id_bom_detail",
          "type": "uuid",
          "primaryKey": true,
          "notNull": true,
          "default": "gen_random_uuid()"
        },
        "bom_id": {
          "name": "bom_id",
          "type": "uuid",
          "primaryKey": false,
          "notNull": true
        },
        "raw_item_id": {
          "name": "raw_item_id",
          "type": "varchar(20)",
          "primaryKey": false,
          "notNull": true
        },
        "qty": {
          "name": "qty",
          "type": "numeric",
          "primaryKey": false,
          "notNull": true
        }
      },
      "indexes": {},
      "foreignKeys": {
        "item_bom_detail_bom_id_item_bom_id_bom_fk": {
          "name": "item_bom_detail_bom_id_item_bom_id_bom_fk",
          "tableFrom": "item_bom_detail",
          "tableTo": "item_bom",
          "columnsFrom": [
            "bom_id"
          ],
          "columnsTo": [
            "id_bom"
          ],
          "onDelete": "cascade",
          "onUpdate": "cascade"
        },
        "item_bom_detail_raw_item_id_item_id_item_fk": {
          "name": "item_bom_detail_raw_item_id_item_id_item_fk",
          "tableFrom": "item_bom_detail",
          "tableTo": "item",
          "columnsFrom": [
            "raw_item_id"
          ],
          "columnsTo": [
            "id_item"
          ],
          "onDelete": "no action",
          "onUpdate": "no action"
        }
      },
      "compositePrimaryKeys": {},
      "uniqueConstraints": {},
      "policies": {},
      "checkConstraints": {},
      "isRLSEnabled": false
    },
    "public.item_bom": {
      "name": "item_bom",
      "schema": "",
      "columns": {
        "id_bom": {
          "name": "id_bom",
          "type": "uuid",
          "primaryKey": true,
          "notNull": true,
          "default": "gen_random_uuid()"
        },
        "item_id": {
          "name": "item_id",
          "type": "varchar(20)",
          "primaryKey": false,
          "notNull": true
        },
        "created_at": {
          "name": "created_at",
          "type": "timestamp",
          "primaryKey": false,
          "notNull": true,
          "default": "now()"
        }
      },
      "indexes": {},
      "foreignKeys": {
        "item_bom_item_id_item_id_item_fk": {
          "name": "item_bom_item_id_item_id_item_fk",
          "tableFrom": "item_bom",
          "tableTo": "item",
          "columnsFrom": [
            "item_id"
          ],
          "columnsTo": [
            "id_item"
          ],
          "onDelete": "cascade",
          "onUpdate": "cascade"
        }
      },
      "compositePrimaryKeys": {},
      "uniqueConstraints": {},
      "policies": {},
      "checkConstraints": {},
      "isRLSEnabled": false
    },
    "public.item_movement": {
      "name": "item_movement",
      "schema": "",
      "columns": {
        "id_movement": {
          "name": "id_movement",
          "type": "uuid",
          "primaryKey": true,
          "notNull": true,
          "default": "gen_random_uuid()"
        },
        "transaction_id": {
          "name": "transaction_id",
          "type": "varchar(20)",
          "primaryKey": false,
          "notNull": false
        },
        "item_id": {
          "name": "item_id",
          "type": "varchar(20)",
          "primaryKey": false,
          "notNull": true
        },
        "type_movement": {
          "name": "type_movement",
          "type": "type_movement",
          "typeSchema": "public",
          "primaryKey": false,
          "notNull": true
        },
        "quantity": {
          "name": "quantity",
          "type": "numeric",
          "primaryKey": false,
          "notNull": true
        },
        "created_at": {
          "name": "created_at",
          "type": "timestamp",
          "primaryKey": false,
          "notNull": true,
          "default": "now()"
        }
      },
      "indexes": {},
      "foreignKeys": {
        "item_movement_transaction_id_transaction_id_transaction_fk": {
          "name": "item_movement_transaction_id_transaction_id_transaction_fk",
          "tableFrom": "item_movement",
          "tableTo": "transaction",
          "columnsFrom": [
            "transaction_id"
          ],
          "columnsTo": [
            "id_transaction"
          ],
          "onDelete": "no action",
          "onUpdate": "no action"
        },
        "item_movement_item_id_item_id_item_fk": {
          "name": "item_movement_item_id_item_id_item_fk",
          "tableFrom": "item_movement",
          "tableTo": "item",
          "columnsFrom": [
            "item_id"
          ],
          "columnsTo": [
            "id_item"
          ],
          "onDelete": "cascade",
          "onUpdate": "cascade"
        }
      },
      "compositePrimaryKeys": {},
      "uniqueConstraints": {},
      "policies": {},
      "checkConstraints": {},
      "isRLSEnabled": false
    },
    "public.item": {
      "name": "item",
      "schema": "",
      "columns": {
        "id_item": {
          "name": "id_item",
          "type": "varchar(20)",
          "primaryKey": true,
          "notNull": true
        },
        "name": {
          "name": "name",
          "type": "varchar(255)",
          "primaryKey": false,
          "notNull": true
        },
        "unit_id": {
          "name": "unit_id",
          "type": "uuid",
          "primaryKey": false,
          "notNull": true
        },
        "category_id": {
          "name": "category_id",
          "type": "uuid",
          "primaryKey": false,
          "notNull": true
        },
        "type_item": {
          "name": "type_item",
          "type": "type_item",
          "typeSchema": "public",
          "primaryKey": false,
          "notNull": true,
          "default": "'RAW_MATERIAL'"
        },
        "min_stock": {
          "name": "min_stock",
          "type": "numeric",
          "primaryKey": false,
          "notNull": true,
          "default": "'0'"
        },
        "created_at": {
          "name": "created_at",
          "type": "timestamp",
          "primaryKey": false,
          "notNull": true,
          "default": "now()"
        }
      },
      "indexes": {},
      "foreignKeys": {
        "item_unit_id_unit_id_unit_fk": {
          "name": "item_unit_id_unit_id_unit_fk",
          "tableFrom": "item",
          "tableTo": "unit",
          "columnsFrom": [
            "unit_id"
          ],
          "columnsTo": [
            "id_unit"
          ],
          "onDelete": "cascade",
          "onUpdate": "cascade"
        },
        "item_category_id_category_id_category_fk": {
          "name": "item_category_id_category_id_category_fk",
          "tableFrom": "item",
          "tableTo": "category",
          "columnsFrom": [
            "category_id"
          ],
          "columnsTo": [
            "id_category"
          ],
          "onDelete": "cascade",
          "onUpdate": "cascade"
        }
      },
      "compositePrimaryKeys": {},
      "uniqueConstraints": {
        "item_name_unique": {
          "name": "item_name_unique",
          "nullsNotDistinct": false,
          "columns": [
            "name"
          ]
        }
      },
      "policies": {},
      "checkConstraints": {},
      "isRLSEnabled": false
    },
    "public.notifications": {
      "name": "notifications",
      "schema": "",
      "columns": {
        "id_notification": {
          "name": "id_notification",
          "type": "uuid",
          "primaryKey": true,
          "notNull": true,
          "default": "gen_random_uuid()"
        },
        "recipient_type": {
          "name": "recipient_type",
          "type": "notification_recipient",
          "typeSchema": "public",
          "primaryKey": false,
          "notNull": true
        },
        "user_id": {
          "name": "user_id",
          "type": "uuid",
          "primaryKey": false,
          "notNull": false
        },
        "supplier_id": {
          "name": "supplier_id",
          "type": "uuid",
          "primaryKey": false,
          "notNull": false
        },
        "ref_type": {
          "name": "ref_type",
          "type": "notification_ref",
          "typeSchema": "public",
          "primaryKey": false,
          "notNull": true
        },
        "ref_id": {
          "name": "ref_id",
          "type": "varchar(20)",
          "primaryKey": false,
          "notNull": true
        },
        "message": {
          "name": "message",
          "type": "text",
          "primaryKey": false,
          "notNull": true
        },
        "status": {
          "name": "status",
          "type": "status_notification",
          "typeSchema": "public",
          "primaryKey": false,
          "notNull": true,
          "default": "'PENDING'"
        },
        "created_at": {
          "name": "created_at",
          "type": "timestamp",
          "primaryKey": false,
          "notNull": true,
          "default": "now()"
        }
      },
      "indexes": {},
      "foreignKeys": {
        "notifications_user_id_user_id_user_fk": {
          "name": "notifications_user_id_user_id_user_fk",
          "tableFrom": "notifications",
          "tableTo": "user",
          "columnsFrom": [
            "user_id"
          ],
          "columnsTo": [
            "id_user"
          ],
          "onDelete": "cascade",
          "onUpdate": "cascade"
        },
        "notifications_supplier_id_supplier_id_supplier_fk": {
          "name": "notifications_supplier_id_supplier_id_supplier_fk",
          "tableFrom": "notifications",
          "tableTo": "supplier",
          "columnsFrom": [
            "supplier_id"
          ],
          "columnsTo": [
            "id_supplier"
          ],
          "onDelete": "cascade",
          "onUpdate": "cascade"
        }
      },
      "compositePrimaryKeys": {},
      "uniqueConstraints": {},
      "policies": {},
      "checkConstraints": {},
      "isRLSEnabled": false
    },
    "public.procurement_item": {
      "name": "procurement_item",
      "schema": "",
      "columns": {
        "id_procurement_item": {
          "name": "id_procurement_item",
          "type": "uuid",
          "primaryKey": true,
          "notNull": true,
          "default": "gen_random_uuid()"
        },
        "procurement_id": {
          "name": "procurement_id",
          "type": "varchar(20)",
          "primaryKey": false,
          "notNull": true
        },
        "item_id": {
          "name": "item_id",
          "type": "varchar(20)",
          "primaryKey": false,
          "notNull": true
        },
        "qty_requested": {
          "name": "qty_requested",
          "type": "numeric",
          "primaryKey": false,
          "notNull": true
        },
        "notes": {
          "name": "notes",
          "type": "text",
          "primaryKey": false,
          "notNull": false
        }
      },
      "indexes": {},
      "foreignKeys": {
        "procurement_item_procurement_id_procurement_id_procurement_fk": {
          "name": "procurement_item_procurement_id_procurement_id_procurement_fk",
          "tableFrom": "procurement_item",
          "tableTo": "procurement",
          "columnsFrom": [
            "procurement_id"
          ],
          "columnsTo": [
            "id_procurement"
          ],
          "onDelete": "cascade",
          "onUpdate": "cascade"
        },
        "procurement_item_item_id_item_id_item_fk": {
          "name": "procurement_item_item_id_item_id_item_fk",
          "tableFrom": "procurement_item",
          "tableTo": "item",
          "columnsFrom": [
            "item_id"
          ],
          "columnsTo": [
            "id_item"
          ],
          "onDelete": "cascade",
          "onUpdate": "cascade"
        }
      },
      "compositePrimaryKeys": {},
      "uniqueConstraints": {},
      "policies": {},
      "checkConstraints": {},
      "isRLSEnabled": false
    },
    "public.procurement": {
      "name": "procurement",
      "schema": "",
      "columns": {
        "id_procurement": {
          "name": "id_procurement",
          "type": "varchar(20)",
          "primaryKey": true,
          "notNull": true
        },
        "requested_by": {
          "name": "requested_by",
          "type": "uuid",
          "primaryKey": false,
          "notNull": true
        },
        "status": {
          "name": "status",
          "type": "procurement_status",
          "typeSchema": "public",
          "primaryKey": false,
          "notNull": true,
          "default": "'DRAFT'"
        },
        "created_at": {
          "name": "created_at",
          "type": "timestamp",
          "primaryKey": false,
          "notNull": true,
          "default": "now()"
        },
        "updated_at": {
          "name": "updated_at",
          "type": "timestamp",
          "primaryKey": false,
          "notNull": true,
          "default": "now()"
        }
      },
      "indexes": {},
      "foreignKeys": {
        "procurement_requested_by_user_id_user_fk": {
          "name": "procurement_requested_by_user_id_user_fk",
          "tableFrom": "procurement",
          "tableTo": "user",
          "columnsFrom": [
            "requested_by"
          ],
          "columnsTo": [
            "id_user"
          ],
          "onDelete": "cascade",
          "onUpdate": "cascade"
        }
      },
      "compositePrimaryKeys": {},
      "uniqueConstraints": {},
      "policies": {},
      "checkConstraints": {},
      "isRLSEnabled": false
    },
    "public.production_material": {
      "name": "production_material",
      "schema": "",
      "columns": {
        "id_production_material": {
          "name": "id_production_material",
          "type": "uuid",
          "primaryKey": true,
          "notNull": true,
          "default": "gen_random_uuid()"
        },
        "production_order_id": {
          "name": "production_order_id",
          "type": "varchar(20)",
          "primaryKey": false,
          "notNull": true
        },
        "bom_detail_id": {
          "name": "bom_detail_id",
          "type": "uuid",
          "primaryKey": false,
          "notNull": true
        },
        "item_id": {
          "name": "item_id",
          "type": "varchar(20)",
          "primaryKey": false,
          "notNull": true
        },
        "qty_required": {
          "name": "qty_required",
          "type": "numeric",
          "primaryKey": false,
          "notNull": true
        },
        "qty_used": {
          "name": "qty_used",
          "type": "numeric",
          "primaryKey": false,
          "notNull": true,
          "default": "'0'"
        }
      },
      "indexes": {},
      "foreignKeys": {
        "production_material_production_order_id_production_order_id_production_order_fk": {
          "name": "production_material_production_order_id_production_order_id_production_order_fk",
          "tableFrom": "production_material",
          "tableTo": "production_order",
          "columnsFrom": [
            "production_order_id"
          ],
          "columnsTo": [
            "id_production_order"
          ],
          "onDelete": "cascade",
          "onUpdate": "cascade"
        },
        "production_material_bom_detail_id_item_bom_detail_id_bom_detail_fk": {
          "name": "production_material_bom_detail_id_item_bom_detail_id_bom_detail_fk",
          "tableFrom": "production_material",
          "tableTo": "item_bom_detail",
          "columnsFrom": [
            "bom_detail_id"
          ],
          "columnsTo": [
            "id_bom_detail"
          ],
          "onDelete": "restrict",
          "onUpdate": "cascade"
        },
        "production_material_item_id_item_id_item_fk": {
          "name": "production_material_item_id_item_id_item_fk",
          "tableFrom": "production_material",
          "tableTo": "item",
          "columnsFrom": [
            "item_id"
          ],
          "columnsTo": [
            "id_item"
          ],
          "onDelete": "restrict",
          "onUpdate": "cascade"
        }
      },
      "compositePrimaryKeys": {},
      "uniqueConstraints": {},
      "policies": {},
      "checkConstraints": {},
      "isRLSEnabled": false
    },
    "public.production_order": {
      "name": "production_order",
      "schema": "",
      "columns": {
        "id_production_order": {
          "name": "id_production_order",
          "type": "varchar(20)",
          "primaryKey": true,
          "notNull": true
        },
        "procurement_id": {
          "name": "procurement_id",
          "type": "varchar(20)",
          "primaryKey": false,
          "notNull": true
        },
        "procurement_item_id": {
          "name": "procurement_item_id",
          "type": "uuid",
          "primaryKey": false,
          "notNull": true
        },
        "item_id": {
          "name": "item_id",
          "type": "varchar(20)",
          "primaryKey": false,
          "notNull": true
        },
        "qty_target": {
          "name": "qty_target",
          "type": "numeric",
          "primaryKey": false,
          "notNull": true
        },
        "qty_produced": {
          "name": "qty_produced",
          "type": "numeric",
          "primaryKey": false,
          "notNull": true,
          "default": "'0'"
        },
        "status": {
          "name": "status",
          "type": "production_status",
          "typeSchema": "public",
          "primaryKey": false,
          "notNull": true,
          "default": "'DRAFT'"
        },
        "scheduled_date": {
          "name": "scheduled_date",
          "type": "timestamp",
          "primaryKey": false,
          "notNull": false
        },
        "completed_date": {
          "name": "completed_date",
          "type": "timestamp",
          "primaryKey": false,
          "notNull": false
        },
        "notes": {
          "name": "notes",
          "type": "text",
          "primaryKey": false,
          "notNull": false
        },
        "created_at": {
          "name": "created_at",
          "type": "timestamp",
          "primaryKey": false,
          "notNull": true,
          "default": "now()"
        }
      },
      "indexes": {},
      "foreignKeys": {
        "production_order_procurement_id_procurement_id_procurement_fk": {
          "name": "production_order_procurement_id_procurement_id_procurement_fk",
          "tableFrom": "production_order",
          "tableTo": "procurement",
          "columnsFrom": [
            "procurement_id"
          ],
          "columnsTo": [
            "id_procurement"
          ],
          "onDelete": "cascade",
          "onUpdate": "cascade"
        },
        "production_order_procurement_item_id_procurement_item_id_procurement_item_fk": {
          "name": "production_order_procurement_item_id_procurement_item_id_procurement_item_fk",
          "tableFrom": "production_order",
          "tableTo": "procurement_item",
          "columnsFrom": [
            "procurement_item_id"
          ],
          "columnsTo": [
            "id_procurement_item"
          ],
          "onDelete": "cascade",
          "onUpdate": "cascade"
        },
        "production_order_item_id_item_id_item_fk": {
          "name": "production_order_item_id_item_id_item_fk",
          "tableFrom": "production_order",
          "tableTo": "item",
          "columnsFrom": [
            "item_id"
          ],
          "columnsTo": [
            "id_item"
          ],
          "onDelete": "restrict",
          "onUpdate": "cascade"
        }
      },
      "compositePrimaryKeys": {},
      "uniqueConstraints": {},
      "policies": {},
      "checkConstraints": {},
      "isRLSEnabled": false
    },
    "public.production_record": {
      "name": "production_record",
      "schema": "",
      "columns": {
        "id_production_record": {
          "name": "id_production_record",
          "type": "varchar(20)",
          "primaryKey": true,
          "notNull": true
        },
        "production_order_id": {
          "name": "production_order_id",
          "type": "varchar(20)",
          "primaryKey": false,
          "notNull": true
        },
        "produced_by": {
          "name": "produced_by",
          "type": "uuid",
          "primaryKey": false,
          "notNull": true
        },
        "qty_produced": {
          "name": "qty_produced",
          "type": "numeric",
          "primaryKey": false,
          "notNull": true
        },
        "notes": {
          "name": "notes",
          "type": "text",
          "primaryKey": false,
          "notNull": false
        },
        "created_at": {
          "name": "created_at",
          "type": "timestamp",
          "primaryKey": false,
          "notNull": true,
          "default": "now()"
        }
      },
      "indexes": {},
      "foreignKeys": {
        "production_record_production_order_id_production_order_id_production_order_fk": {
          "name": "production_record_production_order_id_production_order_id_production_order_fk",
          "tableFrom": "production_record",
          "tableTo": "production_order",
          "columnsFrom": [
            "production_order_id"
          ],
          "columnsTo": [
            "id_production_order"
          ],
          "onDelete": "cascade",
          "onUpdate": "cascade"
        },
        "production_record_produced_by_user_id_user_fk": {
          "name": "production_record_produced_by_user_id_user_fk",
          "tableFrom": "production_record",
          "tableTo": "user",
          "columnsFrom": [
            "produced_by"
          ],
          "columnsTo": [
            "id_user"
          ],
          "onDelete": "restrict",
          "onUpdate": "cascade"
        }
      },
      "compositePrimaryKeys": {},
      "uniqueConstraints": {},
      "policies": {},
      "checkConstraints": {},
      "isRLSEnabled": false
    },
    "public.purchase_item": {
      "name": "purchase_item",
      "schema": "",
      "columns": {
        "id_purchase_item": {
          "name": "id_purchase_item",
          "type": "uuid",
          "primaryKey": true,
          "notNull": true,
          "default": "gen_random_uuid()"
        },
        "purchase_id": {
          "name": "purchase_id",
          "type": "varchar(20)",
          "primaryKey": false,
          "notNull": true
        },
        "procurement_item_id": {
          "name": "procurement_item_id",
          "type": "uuid",
          "primaryKey": false,
          "notNull": true
        },
        "item_id": {
          "name": "item_id",
          "type": "varchar(20)",
          "primaryKey": false,
          "notNull": true
        },
        "qty_ordered": {
          "name": "qty_ordered",
          "type": "numeric",
          "primaryKey": false,
          "notNull": true
        }
      },
      "indexes": {},
      "foreignKeys": {
        "purchase_item_purchase_id_purchase_id_purchase_fk": {
          "name": "purchase_item_purchase_id_purchase_id_purchase_fk",
          "tableFrom": "purchase_item",
          "tableTo": "purchase",
          "columnsFrom": [
            "purchase_id"
          ],
          "columnsTo": [
            "id_purchase"
          ],
          "onDelete": "cascade",
          "onUpdate": "cascade"
        },
        "purchase_item_procurement_item_id_procurement_item_id_procurement_item_fk": {
          "name": "purchase_item_procurement_item_id_procurement_item_id_procurement_item_fk",
          "tableFrom": "purchase_item",
          "tableTo": "procurement_item",
          "columnsFrom": [
            "procurement_item_id"
          ],
          "columnsTo": [
            "id_procurement_item"
          ],
          "onDelete": "cascade",
          "onUpdate": "cascade"
        },
        "purchase_item_item_id_item_id_item_fk": {
          "name": "purchase_item_item_id_item_id_item_fk",
          "tableFrom": "purchase_item",
          "tableTo": "item",
          "columnsFrom": [
            "item_id"
          ],
          "columnsTo": [
            "id_item"
          ],
          "onDelete": "no action",
          "onUpdate": "no action"
        }
      },
      "compositePrimaryKeys": {},
      "uniqueConstraints": {},
      "policies": {},
      "checkConstraints": {},
      "isRLSEnabled": false
    },
    "public.purchase": {
      "name": "purchase",
      "schema": "",
      "columns": {
        "id_purchase": {
          "name": "id_purchase",
          "type": "varchar(20)",
          "primaryKey": true,
          "notNull": true
        },
        "procurement_id": {
          "name": "procurement_id",
          "type": "varchar(20)",
          "primaryKey": false,
          "notNull": true
        },
        "supplier_id": {
          "name": "supplier_id",
          "type": "uuid",
          "primaryKey": false,
          "notNull": true
        },
        "status": {
          "name": "status",
          "type": "purchase_status",
          "typeSchema": "public",
          "primaryKey": false,
          "notNull": true,
          "default": "'DRAFT'"
        },
        "created_at": {
          "name": "created_at",
          "type": "timestamp",
          "primaryKey": false,
          "notNull": true,
          "default": "now()"
        }
      },
      "indexes": {},
      "foreignKeys": {
        "purchase_procurement_id_procurement_id_procurement_fk": {
          "name": "purchase_procurement_id_procurement_id_procurement_fk",
          "tableFrom": "purchase",
          "tableTo": "procurement",
          "columnsFrom": [
            "procurement_id"
          ],
          "columnsTo": [
            "id_procurement"
          ],
          "onDelete": "cascade",
          "onUpdate": "cascade"
        },
        "purchase_supplier_id_supplier_id_supplier_fk": {
          "name": "purchase_supplier_id_supplier_id_supplier_fk",
          "tableFrom": "purchase",
          "tableTo": "supplier",
          "columnsFrom": [
            "supplier_id"
          ],
          "columnsTo": [
            "id_supplier"
          ],
          "onDelete": "cascade",
          "onUpdate": "cascade"
        }
      },
      "compositePrimaryKeys": {},
      "uniqueConstraints": {},
      "policies": {},
      "checkConstraints": {},
      "isRLSEnabled": false
    },
    "public.supplier": {
      "name": "supplier",
      "schema": "",
      "columns": {
        "id_supplier": {
          "name": "id_supplier",
          "type": "uuid",
          "primaryKey": true,
          "notNull": true,
          "default": "gen_random_uuid()"
        },
        "store": {
          "name": "store",
          "type": "varchar(255)",
          "primaryKey": false,
          "notNull": true
        },
        "name": {
          "name": "name",
          "type": "varchar(255)",
          "primaryKey": false,
          "notNull": true
        },
        "phone": {
          "name": "phone",
          "type": "varchar(20)",
          "primaryKey": false,
          "notNull": false
        },
        "address": {
          "name": "address",
          "type": "text",
          "primaryKey": false,
          "notNull": false
        }
      },
      "indexes": {},
      "foreignKeys": {},
      "compositePrimaryKeys": {},
      "uniqueConstraints": {
        "supplier_phone_unique": {
          "name": "supplier_phone_unique",
          "nullsNotDistinct": false,
          "columns": [
            "phone"
          ]
        }
      },
      "policies": {},
      "checkConstraints": {},
      "isRLSEnabled": false
    },
    "public.transaction": {
      "name": "transaction",
      "schema": "",
      "columns": {
        "id_transaction": {
          "name": "id_transaction",
          "type": "varchar(20)",
          "primaryKey": true,
          "notNull": true
        },
        "type_transaction": {
          "name": "type_transaction",
          "type": "type_transaction",
          "typeSchema": "public",
          "primaryKey": false,
          "notNull": true
        },
        "status_transaction": {
          "name": "status_transaction",
          "type": "status_transaction",
          "typeSchema": "public",
          "primaryKey": false,
          "notNull": true,
          "default": "'PENDING'"
        },
        "user_id": {
          "name": "user_id",
          "type": "uuid",
          "primaryKey": false,
          "notNull": true
        },
        "created_at": {
          "name": "created_at",
          "type": "timestamp",
          "primaryKey": false,
          "notNull": true,
          "default": "now()"
        }
      },
      "indexes": {},
      "foreignKeys": {
        "transaction_user_id_user_id_user_fk": {
          "name": "transaction_user_id_user_id_user_fk",
          "tableFrom": "transaction",
          "tableTo": "user",
          "columnsFrom": [
            "user_id"
          ],
          "columnsTo": [
            "id_user"
          ],
          "onDelete": "cascade",
          "onUpdate": "cascade"
        }
      },
      "compositePrimaryKeys": {},
      "uniqueConstraints": {},
      "policies": {},
      "checkConstraints": {},
      "isRLSEnabled": false
    },
    "public.unit": {
      "name": "unit",
      "schema": "",
      "columns": {
        "id_unit": {
          "name": "id_unit",
          "type": "uuid",
          "primaryKey": true,
          "notNull": true,
          "default": "gen_random_uuid()"
        },
        "name": {
          "name": "name",
          "type": "varchar(50)",
          "primaryKey": false,
          "notNull": true
        }
      },
      "indexes": {},
      "foreignKeys": {},
      "compositePrimaryKeys": {},
      "uniqueConstraints": {
        "unit_name_unique": {
          "name": "unit_name_unique",
          "nullsNotDistinct": false,
          "columns": [
            "name"
          ]
        }
      },
      "policies": {},
      "checkConstraints": {},
      "isRLSEnabled": false
    },
    "public.user": {
      "name": "user",
      "schema": "",
      "columns": {
        "id_user": {
          "name": "id_user",
          "type": "uuid",
          "primaryKey": true,
          "notNull": true,
          "default": "gen_random_uuid()"
        },
        "name": {
          "name": "name",
          "type": "varchar(255)",
          "primaryKey": false,
          "notNull": true
        },
        "username": {
          "name": "username",
          "type": "varchar(255)",
          "primaryKey": false,
          "notNull": true
        },
        "password": {
          "name": "password",
          "type": "varchar(255)",
          "primaryKey": false,
          "notNull": true
        },
        "phone": {
          "name": "phone",
          "type": "varchar(20)",
          "primaryKey": false,
          "notNull": true
        },
        "role": {
          "name": "role",
          "type": "user_role",
          "typeSchema": "public",
          "primaryKey": false,
          "notNull": true,
          "default": "'HEADKITCHEN'"
        },
        "created_at": {
          "name": "created_at",
          "type": "timestamp",
          "primaryKey": false,
          "notNull": true,
          "default": "now()"
        }
      },
      "indexes": {},
      "foreignKeys": {},
      "compositePrimaryKeys": {},
      "uniqueConstraints": {
        "user_username_unique": {
          "name": "user_username_unique",
          "nullsNotDistinct": false,
          "columns": [
            "username"
          ]
        },
        "user_phone_unique": {
          "name": "user_phone_unique",
          "nullsNotDistinct": false,
          "columns": [
            "phone"
          ]
        }
      },
      "policies": {},
      "checkConstraints": {},
      "isRLSEnabled": false
    }
  },
  "enums": {
    "public.notification_recipient": {
      "name": "notification_recipient",
      "schema": "public",
      "values": [
        "USER",
        "SUPPLIER"
      ]
    },
    "public.notification_ref": {
      "name": "notification_ref",
      "schema": "public",
      "values": [
        "PROCUREMENT",
        "PURCHASE",
        "RECEIPT",
        "RETURN"
      ]
    },
    "public.procurement_status": {
      "name": "procurement_status",
      "schema": "public",
      "values": [
        "DRAFT",
        "ON_PROGRESS",
        "COMPLETED",
        "CANCELLED"
      ]
    },
    "public.production_status": {
      "name": "production_status",
      "schema": "public",
      "values": [
        "DRAFT",
        "SCHEDULED",
        "IN_PROGRESS",
        "COMPLETED",
        "CANCELLED"
      ]
    },
    "public.purchase_status": {
      "name": "purchase_status",
      "schema": "public",
      "values": [
        "DRAFT",
        "SENT",
        "RECEIVED",
        "COMPLETED",
        "CANCELLED"
      ]
    },
    "public.status_notification": {
      "name": "status_notification",
      "schema": "public",
      "values": [
        "PENDING",
        "ONPROGRESS",
        "SENT",
        "FAILED"
      ]
    },
    "public.status_transaction": {
      "name": "status_transaction",
      "schema": "public",
      "values": [
        "PENDING",
        "COMPLETED",
        "CANCELLED"
      ]
    },
    "public.type_item": {
      "name": "type_item",
      "schema": "public",
      "values": [
        "RAW_MATERIAL",
        "WORK_IN_PROGRESS",
        "FINISHED_GOOD"
      ]
    },
    "public.type_movement": {
      "name": "type_movement",
      "schema": "public",
      "values": [
        "IN",
        "OUT"
      ]
    },
    "public.type_transaction": {
      "name": "type_transaction",
      "schema": "public",
      "values": [
        "PURCHASE",
        "PRODUCTION",
        "SALES",
        "ADJUSTMENT"
      ]
    },
    "public.user_role": {
      "name": "user_role",
      "schema": "public",
      "values": [
        "SUPER_ADMIN",
        "ADMIN",
        "HEADKITCHEN",
        "KITCHEN",
        "MANAGER"
      ]
    }
  },
  "schemas": {},
  "sequences": {},
  "roles": {},
  "policies": {},
  "views": {},
  "_meta": {
    "columns": {},
    "schemas": {},
    "tables": {}
  }
}